{
  "teamId": "exampleTeam1",
  "nav": [
    {
      "text": "App1",
      "url": "/site/example-team1-url/app1-url",
      "moduleFederationComponentId": "example-team1__app1__app"
    },
    {
      "text": "App2",
      "url": "/site/example-team1-url/app2-url",
      "moduleFederationComponentId": "example-team1__app2__app"
    }
  ],
  "apps": {
    "example-team1__app1__app": {
      "scope": "exampleTeam1__app1",
      "module": "./app",
      "remoteEntryUrl": "/assets/example-team1__app1/remoteEntry.js"
    },
    "example-team1__app2__app": {
      "scope": "exampleTeam1__app2",
      "module": "./app",
      "remoteEntryUrl": "/assets/example-team1__app2/remoteEntry.js"
    }
  }
}
